xdev/__init__.py
xdev/__main__.py
xdev/__main__.pyi
xdev/_ipython_ext.py
xdev/_ipython_ext.pyi
xdev/algo.py
xdev/algo.pyi
xdev/autojit.py
xdev/autojit.pyi
xdev/class_reloader.py
xdev/class_reloader.pyi
xdev/desktop_interaction.py
xdev/desktop_interaction.pyi
xdev/directory_walker.py
xdev/embeding.py
xdev/embeding.pyi
xdev/format_quotes.py
xdev/format_quotes.pyi
xdev/interactive_iter.py
xdev/interactive_iter.pyi
xdev/introspect.py
xdev/introspect.pyi
xdev/misc.py
xdev/misc.pyi
xdev/patterns.py
xdev/patterns.pyi
xdev/profiler.py
xdev/profiler.pyi
xdev/py.typed
xdev/regex_builder.py
xdev/regex_builder.pyi
xdev/search_replace.py
xdev/search_replace.pyi
xdev/static_analysis.py
xdev/tracebacks.py
xdev/tracebacks.pyi
xdev/util.py
xdev/util.pyi
xdev/util_networkx.py
xdev/util_networkx.pyi
xdev/util_path.py
xdev/util_path.pyi
xdev/util_random.py
xdev/util_time.py
xdev/cli/__init__.py
xdev/cli/__main__.py
xdev/cli/__main__.pyi
xdev/cli/available_package_versions.py
xdev/cli/available_package_versions.pyi
xdev/cli/dirstats.py
xdev/cli/docstr_stubgen.py
xdev/cli/main.py
xdev/cli/main.pyi
xdev/cli/pypackage_summary.py
xdev/cli/pyversion_cli.py
xdev-1.5.4.data/scripts/freshpyenv.sh
xdev-1.5.4.dist-info/LICENSE
xdev-1.5.4.dist-info/METADATA
xdev-1.5.4.dist-info/WHEEL
xdev-1.5.4.dist-info/entry_points.txt
xdev-1.5.4.dist-info/top_level.txt
xdev-1.5.4.dist-info/RECORD
