Metadata-Version: 2.2
Name: xdev
Version: 1.5.4
Summary: An excellent developer tool for excellent developers
Home-page: https://github.com/Erotemic/xdev
Author: Jon Crall
Author-email: erotemic@gmail.com
License: Apache 2
Classifier: Development Status :: 4 - Beta
Classifier: Intended Audience :: Developers
Classifier: Topic :: Software Development :: Libraries :: Python Modules
Classifier: Topic :: Utilities
Classifier: License :: OSI Approved :: Apache Software License
Classifier: Programming Language :: Python :: 3.8
Classifier: Programming Language :: Python :: 3.9
Classifier: Programming Language :: Python :: 3.10
Classifier: Programming Language :: Python :: 3.11
Classifier: Programming Language :: Python :: 3.12
Classifier: Programming Language :: Python :: 3.13
Requires-Python: >=3.8
License-File: LICENSE
Requires-Dist: ubelt>=1.3.3
Requires-Dist: xinspect>=0.4.0
Requires-Dist: pyfiglet>=0.7
Requires-Dist: pygments>=2.12.0
Requires-Dist: IPython>=7.16.2
Requires-Dist: parse>=1.19.0
Requires-Dist: pyflakes>=2.5.0
Requires-Dist: scriptconfig>=0.7.10
Requires-Dist: lazy_loader>=0.3
Requires-Dist: numpy>=2.1.0; python_version < "4.0" and python_version >= "3.13"
Requires-Dist: numpy>=1.26.0; python_version < "3.13" and python_version >= "3.12"
Requires-Dist: numpy>=1.23.2; python_version < "3.12" and python_version >= "3.11"
Requires-Dist: numpy>=1.21.6; python_version < "3.11" and python_version >= "3.10"
Requires-Dist: numpy>=1.21.0; python_version < "3.10" and python_version >= "3.9"
Requires-Dist: numpy>=1.21.0; python_version < "3.9" and python_version >= "3.8"
Requires-Dist: networkx>=3.1; python_version < "4.0" and python_version >= "3.11"
Requires-Dist: networkx>=3.1; python_version < "3.11" and python_version >= "3.10"
Requires-Dist: networkx>=3.1; python_version < "3.10" and python_version >= "3.9"
Requires-Dist: networkx>=3.1; python_version < "3.9" and python_version >= "3.8"
Requires-Dist: rich>=12.3.0
Requires-Dist: progiter>=2.0.0
Provides-Extra: all
Requires-Dist: ubelt>=1.3.3; extra == "all"
Requires-Dist: xinspect>=0.4.0; extra == "all"
Requires-Dist: pyfiglet>=0.7; extra == "all"
Requires-Dist: pygments>=2.12.0; extra == "all"
Requires-Dist: IPython>=7.16.2; extra == "all"
Requires-Dist: parse>=1.19.0; extra == "all"
Requires-Dist: pyflakes>=2.5.0; extra == "all"
Requires-Dist: scriptconfig>=0.7.10; extra == "all"
Requires-Dist: lazy_loader>=0.3; extra == "all"
Requires-Dist: numpy>=2.1.0; (python_version < "4.0" and python_version >= "3.13") and extra == "all"
Requires-Dist: numpy>=1.26.0; (python_version < "3.13" and python_version >= "3.12") and extra == "all"
Requires-Dist: numpy>=1.23.2; (python_version < "3.12" and python_version >= "3.11") and extra == "all"
Requires-Dist: numpy>=1.21.6; (python_version < "3.11" and python_version >= "3.10") and extra == "all"
Requires-Dist: numpy>=1.21.0; (python_version < "3.10" and python_version >= "3.9") and extra == "all"
Requires-Dist: numpy>=1.21.0; (python_version < "3.9" and python_version >= "3.8") and extra == "all"
Requires-Dist: networkx>=3.1; (python_version < "4.0" and python_version >= "3.11") and extra == "all"
Requires-Dist: networkx>=3.1; (python_version < "3.11" and python_version >= "3.10") and extra == "all"
Requires-Dist: networkx>=3.1; (python_version < "3.10" and python_version >= "3.9") and extra == "all"
Requires-Dist: networkx>=3.1; (python_version < "3.9" and python_version >= "3.8") and extra == "all"
Requires-Dist: rich>=12.3.0; extra == "all"
Requires-Dist: progiter>=2.0.0; extra == "all"
Requires-Dist: xdoctest>=1.1.5; extra == "all"
Requires-Dist: pytest>=7.0.0; (python_version < "4.0" and python_version >= "3.11") and extra == "all"
Requires-Dist: pytest>=6.2.5; (python_version < "3.11" and python_version >= "3.10") and extra == "all"
Requires-Dist: pytest>=4.6.0; (python_version < "3.10.0" and python_version >= "3.7.0") and extra == "all"
Requires-Dist: pytest>=4.6.0; (python_version < "3.7.0" and python_version >= "3.6.0") and extra == "all"
Requires-Dist: pytest-cov>=3.0.0; python_version >= "3.6.0" and extra == "all"
Requires-Dist: coverage>=6.1.1; python_version >= "3.10" and extra == "all"
Requires-Dist: coverage>=5.3.1; (python_version < "3.10" and python_version >= "3.9") and extra == "all"
Requires-Dist: coverage>=6.1.1; (python_version < "3.9" and python_version >= "3.8") and extra == "all"
Requires-Dist: coverage>=6.1.1; (python_version < "3.8" and python_version >= "3.7") and extra == "all"
Requires-Dist: coverage>=6.1.1; (python_version < "3.7" and python_version >= "3.6") and extra == "all"
Requires-Dist: Levenshtein>=0.26.1; (python_version < "4.0" and python_version >= "3.13") and extra == "all"
Requires-Dist: Levenshtein>=0.23.0; (python_version < "3.13" and python_version >= "3.12") and extra == "all"
Requires-Dist: Levenshtein>=0.20.3; (python_version < "3.12" and python_version >= "3.11") and extra == "all"
Requires-Dist: Levenshtein>=0.18.2; (python_version < "3.11" and python_version >= "3.10") and extra == "all"
Requires-Dist: Levenshtein>=0.18.0; (python_version < "3.10" and python_version >= "3.9") and extra == "all"
Requires-Dist: Levenshtein>=0.18.0; (python_version < "3.9" and python_version >= "3.8") and extra == "all"
Requires-Dist: Levenshtein>=0.18.0; (python_version < "3.8" and python_version >= "3.7") and extra == "all"
Requires-Dist: Levenshtein>=0.18.0; (python_version < "3.7" and python_version >= "3.6") and extra == "all"
Requires-Dist: fire>=0.5.0; python_version >= "3.10" and extra == "all"
Requires-Dist: fire>=0.4.0; python_version < "3.10" and extra == "all"
Requires-Dist: line_profiler>=4.2.0; (python_version < "4.0" and python_version >= "3.13") and extra == "all"
Requires-Dist: line_profiler>=4.1.2; (python_version < "3.13" and python_version >= "3.12") and extra == "all"
Requires-Dist: line_profiler>=4.1.0; (python_version < "3.12" and python_version >= "3.11") and extra == "all"
Requires-Dist: line_profiler>=4.1.0; (python_version < "3.11" and python_version >= "3.10") and extra == "all"
Requires-Dist: line_profiler>=4.1.0; (python_version < "3.10" and python_version >= "3.9") and extra == "all"
Requires-Dist: line_profiler>=4.1.0; (python_version < "3.9" and python_version >= "3.8") and extra == "all"
Requires-Dist: line_profiler>=4.1.0; (python_version < "3.8" and python_version >= "3.7") and extra == "all"
Requires-Dist: line_profiler>=4.1.0; (python_version < "3.7" and python_version >= "3.6") and extra == "all"
Requires-Dist: yapf>=0.16.3; extra == "all"
Requires-Dist: autoflake>=1.5.0; extra == "all"
Requires-Dist: parso>=0.8.4; (python_version < "4.0" and python_version >= "3.12") and extra == "all"
Requires-Dist: parso>=0.8.3; (python_version < "3.12" and python_version >= "3.11") and extra == "all"
Requires-Dist: parso>=0.8.0; python_version < "3.11" and extra == "all"
Requires-Dist: pint>=0.24.4; (python_version < "4.0" and python_version >= "3.13") and extra == "all"
Requires-Dist: pint>=0.23; (python_version < "3.13" and python_version >= "3.12") and extra == "all"
Requires-Dist: pint>=0.18; (python_version < "3.12" and python_version >= "3.11") and extra == "all"
Requires-Dist: pint>=0.18; (python_version < "3.11" and python_version >= "3.10") and extra == "all"
Requires-Dist: pint>=0.18; (python_version < "3.10" and python_version >= "3.9") and extra == "all"
Requires-Dist: pint>=0.18; (python_version < "3.9" and python_version >= "3.8") and extra == "all"
Requires-Dist: python_dateutil>=2.8.2; extra == "all"
Requires-Dist: pytimeparse>=1.1.8; extra == "all"
Provides-Extra: runtime
Requires-Dist: ubelt>=1.3.3; extra == "runtime"
Requires-Dist: xinspect>=0.4.0; extra == "runtime"
Requires-Dist: pyfiglet>=0.7; extra == "runtime"
Requires-Dist: pygments>=2.12.0; extra == "runtime"
Requires-Dist: IPython>=7.16.2; extra == "runtime"
Requires-Dist: parse>=1.19.0; extra == "runtime"
Requires-Dist: pyflakes>=2.5.0; extra == "runtime"
Requires-Dist: scriptconfig>=0.7.10; extra == "runtime"
Requires-Dist: lazy_loader>=0.3; extra == "runtime"
Requires-Dist: numpy>=2.1.0; (python_version < "4.0" and python_version >= "3.13") and extra == "runtime"
Requires-Dist: numpy>=1.26.0; (python_version < "3.13" and python_version >= "3.12") and extra == "runtime"
Requires-Dist: numpy>=1.23.2; (python_version < "3.12" and python_version >= "3.11") and extra == "runtime"
Requires-Dist: numpy>=1.21.6; (python_version < "3.11" and python_version >= "3.10") and extra == "runtime"
Requires-Dist: numpy>=1.21.0; (python_version < "3.10" and python_version >= "3.9") and extra == "runtime"
Requires-Dist: numpy>=1.21.0; (python_version < "3.9" and python_version >= "3.8") and extra == "runtime"
Requires-Dist: networkx>=3.1; (python_version < "4.0" and python_version >= "3.11") and extra == "runtime"
Requires-Dist: networkx>=3.1; (python_version < "3.11" and python_version >= "3.10") and extra == "runtime"
Requires-Dist: networkx>=3.1; (python_version < "3.10" and python_version >= "3.9") and extra == "runtime"
Requires-Dist: networkx>=3.1; (python_version < "3.9" and python_version >= "3.8") and extra == "runtime"
Requires-Dist: rich>=12.3.0; extra == "runtime"
Requires-Dist: progiter>=2.0.0; extra == "runtime"
Provides-Extra: tests
Requires-Dist: xdoctest>=1.1.5; extra == "tests"
Requires-Dist: pytest>=7.0.0; (python_version < "4.0" and python_version >= "3.11") and extra == "tests"
Requires-Dist: pytest>=6.2.5; (python_version < "3.11" and python_version >= "3.10") and extra == "tests"
Requires-Dist: pytest>=4.6.0; (python_version < "3.10.0" and python_version >= "3.7.0") and extra == "tests"
Requires-Dist: pytest>=4.6.0; (python_version < "3.7.0" and python_version >= "3.6.0") and extra == "tests"
Requires-Dist: pytest-cov>=3.0.0; python_version >= "3.6.0" and extra == "tests"
Requires-Dist: coverage>=6.1.1; python_version >= "3.10" and extra == "tests"
Requires-Dist: coverage>=5.3.1; (python_version < "3.10" and python_version >= "3.9") and extra == "tests"
Requires-Dist: coverage>=6.1.1; (python_version < "3.9" and python_version >= "3.8") and extra == "tests"
Requires-Dist: coverage>=6.1.1; (python_version < "3.8" and python_version >= "3.7") and extra == "tests"
Requires-Dist: coverage>=6.1.1; (python_version < "3.7" and python_version >= "3.6") and extra == "tests"
Provides-Extra: optional
Requires-Dist: Levenshtein>=0.26.1; (python_version < "4.0" and python_version >= "3.13") and extra == "optional"
Requires-Dist: Levenshtein>=0.23.0; (python_version < "3.13" and python_version >= "3.12") and extra == "optional"
Requires-Dist: Levenshtein>=0.20.3; (python_version < "3.12" and python_version >= "3.11") and extra == "optional"
Requires-Dist: Levenshtein>=0.18.2; (python_version < "3.11" and python_version >= "3.10") and extra == "optional"
Requires-Dist: Levenshtein>=0.18.0; (python_version < "3.10" and python_version >= "3.9") and extra == "optional"
Requires-Dist: Levenshtein>=0.18.0; (python_version < "3.9" and python_version >= "3.8") and extra == "optional"
Requires-Dist: Levenshtein>=0.18.0; (python_version < "3.8" and python_version >= "3.7") and extra == "optional"
Requires-Dist: Levenshtein>=0.18.0; (python_version < "3.7" and python_version >= "3.6") and extra == "optional"
Requires-Dist: fire>=0.5.0; python_version >= "3.10" and extra == "optional"
Requires-Dist: fire>=0.4.0; python_version < "3.10" and extra == "optional"
Requires-Dist: line_profiler>=4.2.0; (python_version < "4.0" and python_version >= "3.13") and extra == "optional"
Requires-Dist: line_profiler>=4.1.2; (python_version < "3.13" and python_version >= "3.12") and extra == "optional"
Requires-Dist: line_profiler>=4.1.0; (python_version < "3.12" and python_version >= "3.11") and extra == "optional"
Requires-Dist: line_profiler>=4.1.0; (python_version < "3.11" and python_version >= "3.10") and extra == "optional"
Requires-Dist: line_profiler>=4.1.0; (python_version < "3.10" and python_version >= "3.9") and extra == "optional"
Requires-Dist: line_profiler>=4.1.0; (python_version < "3.9" and python_version >= "3.8") and extra == "optional"
Requires-Dist: line_profiler>=4.1.0; (python_version < "3.8" and python_version >= "3.7") and extra == "optional"
Requires-Dist: line_profiler>=4.1.0; (python_version < "3.7" and python_version >= "3.6") and extra == "optional"
Requires-Dist: yapf>=0.16.3; extra == "optional"
Requires-Dist: autoflake>=1.5.0; extra == "optional"
Requires-Dist: parso>=0.8.4; (python_version < "4.0" and python_version >= "3.12") and extra == "optional"
Requires-Dist: parso>=0.8.3; (python_version < "3.12" and python_version >= "3.11") and extra == "optional"
Requires-Dist: parso>=0.8.0; python_version < "3.11" and extra == "optional"
Requires-Dist: pint>=0.24.4; (python_version < "4.0" and python_version >= "3.13") and extra == "optional"
Requires-Dist: pint>=0.23; (python_version < "3.13" and python_version >= "3.12") and extra == "optional"
Requires-Dist: pint>=0.18; (python_version < "3.12" and python_version >= "3.11") and extra == "optional"
Requires-Dist: pint>=0.18; (python_version < "3.11" and python_version >= "3.10") and extra == "optional"
Requires-Dist: pint>=0.18; (python_version < "3.10" and python_version >= "3.9") and extra == "optional"
Requires-Dist: pint>=0.18; (python_version < "3.9" and python_version >= "3.8") and extra == "optional"
Requires-Dist: python_dateutil>=2.8.2; extra == "optional"
Requires-Dist: pytimeparse>=1.1.8; extra == "optional"
Provides-Extra: docs
Requires-Dist: sphinx>=4.3.2; extra == "docs"
Requires-Dist: sphinx-autobuild>=2021.3.14; extra == "docs"
Requires-Dist: sphinx_rtd_theme>=1.0.0; extra == "docs"
Requires-Dist: sphinxcontrib-napoleon>=0.7; extra == "docs"
Requires-Dist: sphinx-autoapi>=1.8.4; extra == "docs"
Requires-Dist: Pygments>=2.9.0; extra == "docs"
Requires-Dist: myst_parser>=0.16.1; extra == "docs"
Requires-Dist: sphinx-reredirects>=0.0.1; extra == "docs"
Provides-Extra: all-strict
Requires-Dist: ubelt==1.3.3; extra == "all-strict"
Requires-Dist: xinspect==0.4.0; extra == "all-strict"
Requires-Dist: pyfiglet==0.7; extra == "all-strict"
Requires-Dist: pygments==2.12.0; extra == "all-strict"
Requires-Dist: IPython==7.16.2; extra == "all-strict"
Requires-Dist: parse==1.19.0; extra == "all-strict"
Requires-Dist: pyflakes==2.5.0; extra == "all-strict"
Requires-Dist: scriptconfig==0.7.10; extra == "all-strict"
Requires-Dist: lazy_loader==0.3; extra == "all-strict"
Requires-Dist: numpy==2.1.0; (python_version < "4.0" and python_version >= "3.13") and extra == "all-strict"
Requires-Dist: numpy==1.26.0; (python_version < "3.13" and python_version >= "3.12") and extra == "all-strict"
Requires-Dist: numpy==1.23.2; (python_version < "3.12" and python_version >= "3.11") and extra == "all-strict"
Requires-Dist: numpy==1.21.6; (python_version < "3.11" and python_version >= "3.10") and extra == "all-strict"
Requires-Dist: numpy==1.21.0; (python_version < "3.10" and python_version >= "3.9") and extra == "all-strict"
Requires-Dist: numpy==1.21.0; (python_version < "3.9" and python_version >= "3.8") and extra == "all-strict"
Requires-Dist: networkx==3.1; (python_version < "4.0" and python_version >= "3.11") and extra == "all-strict"
Requires-Dist: networkx==3.1; (python_version < "3.11" and python_version >= "3.10") and extra == "all-strict"
Requires-Dist: networkx==3.1; (python_version < "3.10" and python_version >= "3.9") and extra == "all-strict"
Requires-Dist: networkx==3.1; (python_version < "3.9" and python_version >= "3.8") and extra == "all-strict"
Requires-Dist: rich==12.3.0; extra == "all-strict"
Requires-Dist: progiter==2.0.0; extra == "all-strict"
Requires-Dist: xdoctest==1.1.5; extra == "all-strict"
Requires-Dist: pytest==7.0.0; (python_version < "4.0" and python_version >= "3.11") and extra == "all-strict"
Requires-Dist: pytest==6.2.5; (python_version < "3.11" and python_version >= "3.10") and extra == "all-strict"
Requires-Dist: pytest==4.6.0; (python_version < "3.10.0" and python_version >= "3.7.0") and extra == "all-strict"
Requires-Dist: pytest==4.6.0; (python_version < "3.7.0" and python_version >= "3.6.0") and extra == "all-strict"
Requires-Dist: pytest-cov==3.0.0; python_version >= "3.6.0" and extra == "all-strict"
Requires-Dist: coverage==6.1.1; python_version >= "3.10" and extra == "all-strict"
Requires-Dist: coverage==5.3.1; (python_version < "3.10" and python_version >= "3.9") and extra == "all-strict"
Requires-Dist: coverage==6.1.1; (python_version < "3.9" and python_version >= "3.8") and extra == "all-strict"
Requires-Dist: coverage==6.1.1; (python_version < "3.8" and python_version >= "3.7") and extra == "all-strict"
Requires-Dist: coverage==6.1.1; (python_version < "3.7" and python_version >= "3.6") and extra == "all-strict"
Requires-Dist: Levenshtein==0.26.1; (python_version < "4.0" and python_version >= "3.13") and extra == "all-strict"
Requires-Dist: Levenshtein==0.23.0; (python_version < "3.13" and python_version >= "3.12") and extra == "all-strict"
Requires-Dist: Levenshtein==0.20.3; (python_version < "3.12" and python_version >= "3.11") and extra == "all-strict"
Requires-Dist: Levenshtein==0.18.2; (python_version < "3.11" and python_version >= "3.10") and extra == "all-strict"
Requires-Dist: Levenshtein==0.18.0; (python_version < "3.10" and python_version >= "3.9") and extra == "all-strict"
Requires-Dist: Levenshtein==0.18.0; (python_version < "3.9" and python_version >= "3.8") and extra == "all-strict"
Requires-Dist: Levenshtein==0.18.0; (python_version < "3.8" and python_version >= "3.7") and extra == "all-strict"
Requires-Dist: Levenshtein==0.18.0; (python_version < "3.7" and python_version >= "3.6") and extra == "all-strict"
Requires-Dist: fire==0.5.0; python_version >= "3.10" and extra == "all-strict"
Requires-Dist: fire==0.4.0; python_version < "3.10" and extra == "all-strict"
Requires-Dist: line_profiler==4.2.0; (python_version < "4.0" and python_version >= "3.13") and extra == "all-strict"
Requires-Dist: line_profiler==4.1.2; (python_version < "3.13" and python_version >= "3.12") and extra == "all-strict"
Requires-Dist: line_profiler==4.1.0; (python_version < "3.12" and python_version >= "3.11") and extra == "all-strict"
Requires-Dist: line_profiler==4.1.0; (python_version < "3.11" and python_version >= "3.10") and extra == "all-strict"
Requires-Dist: line_profiler==4.1.0; (python_version < "3.10" and python_version >= "3.9") and extra == "all-strict"
Requires-Dist: line_profiler==4.1.0; (python_version < "3.9" and python_version >= "3.8") and extra == "all-strict"
Requires-Dist: line_profiler==4.1.0; (python_version < "3.8" and python_version >= "3.7") and extra == "all-strict"
Requires-Dist: line_profiler==4.1.0; (python_version < "3.7" and python_version >= "3.6") and extra == "all-strict"
Requires-Dist: yapf==0.16.3; extra == "all-strict"
Requires-Dist: autoflake==1.5.0; extra == "all-strict"
Requires-Dist: parso==0.8.4; (python_version < "4.0" and python_version >= "3.12") and extra == "all-strict"
Requires-Dist: parso==0.8.3; (python_version < "3.12" and python_version >= "3.11") and extra == "all-strict"
Requires-Dist: parso==0.8.0; python_version < "3.11" and extra == "all-strict"
Requires-Dist: pint==0.24.4; (python_version < "4.0" and python_version >= "3.13") and extra == "all-strict"
Requires-Dist: pint==0.23; (python_version < "3.13" and python_version >= "3.12") and extra == "all-strict"
Requires-Dist: pint==0.18; (python_version < "3.12" and python_version >= "3.11") and extra == "all-strict"
Requires-Dist: pint==0.18; (python_version < "3.11" and python_version >= "3.10") and extra == "all-strict"
Requires-Dist: pint==0.18; (python_version < "3.10" and python_version >= "3.9") and extra == "all-strict"
Requires-Dist: pint==0.18; (python_version < "3.9" and python_version >= "3.8") and extra == "all-strict"
Requires-Dist: python_dateutil==2.8.2; extra == "all-strict"
Requires-Dist: pytimeparse==1.1.8; extra == "all-strict"
Provides-Extra: runtime-strict
Requires-Dist: ubelt==1.3.3; extra == "runtime-strict"
Requires-Dist: xinspect==0.4.0; extra == "runtime-strict"
Requires-Dist: pyfiglet==0.7; extra == "runtime-strict"
Requires-Dist: pygments==2.12.0; extra == "runtime-strict"
Requires-Dist: IPython==7.16.2; extra == "runtime-strict"
Requires-Dist: parse==1.19.0; extra == "runtime-strict"
Requires-Dist: pyflakes==2.5.0; extra == "runtime-strict"
Requires-Dist: scriptconfig==0.7.10; extra == "runtime-strict"
Requires-Dist: lazy_loader==0.3; extra == "runtime-strict"
Requires-Dist: numpy==2.1.0; (python_version < "4.0" and python_version >= "3.13") and extra == "runtime-strict"
Requires-Dist: numpy==1.26.0; (python_version < "3.13" and python_version >= "3.12") and extra == "runtime-strict"
Requires-Dist: numpy==1.23.2; (python_version < "3.12" and python_version >= "3.11") and extra == "runtime-strict"
Requires-Dist: numpy==1.21.6; (python_version < "3.11" and python_version >= "3.10") and extra == "runtime-strict"
Requires-Dist: numpy==1.21.0; (python_version < "3.10" and python_version >= "3.9") and extra == "runtime-strict"
Requires-Dist: numpy==1.21.0; (python_version < "3.9" and python_version >= "3.8") and extra == "runtime-strict"
Requires-Dist: networkx==3.1; (python_version < "4.0" and python_version >= "3.11") and extra == "runtime-strict"
Requires-Dist: networkx==3.1; (python_version < "3.11" and python_version >= "3.10") and extra == "runtime-strict"
Requires-Dist: networkx==3.1; (python_version < "3.10" and python_version >= "3.9") and extra == "runtime-strict"
Requires-Dist: networkx==3.1; (python_version < "3.9" and python_version >= "3.8") and extra == "runtime-strict"
Requires-Dist: rich==12.3.0; extra == "runtime-strict"
Requires-Dist: progiter==2.0.0; extra == "runtime-strict"
Provides-Extra: tests-strict
Requires-Dist: xdoctest==1.1.5; extra == "tests-strict"
Requires-Dist: pytest==7.0.0; (python_version < "4.0" and python_version >= "3.11") and extra == "tests-strict"
Requires-Dist: pytest==6.2.5; (python_version < "3.11" and python_version >= "3.10") and extra == "tests-strict"
Requires-Dist: pytest==4.6.0; (python_version < "3.10.0" and python_version >= "3.7.0") and extra == "tests-strict"
Requires-Dist: pytest==4.6.0; (python_version < "3.7.0" and python_version >= "3.6.0") and extra == "tests-strict"
Requires-Dist: pytest-cov==3.0.0; python_version >= "3.6.0" and extra == "tests-strict"
Requires-Dist: coverage==6.1.1; python_version >= "3.10" and extra == "tests-strict"
Requires-Dist: coverage==5.3.1; (python_version < "3.10" and python_version >= "3.9") and extra == "tests-strict"
Requires-Dist: coverage==6.1.1; (python_version < "3.9" and python_version >= "3.8") and extra == "tests-strict"
Requires-Dist: coverage==6.1.1; (python_version < "3.8" and python_version >= "3.7") and extra == "tests-strict"
Requires-Dist: coverage==6.1.1; (python_version < "3.7" and python_version >= "3.6") and extra == "tests-strict"
Provides-Extra: optional-strict
Requires-Dist: Levenshtein==0.26.1; (python_version < "4.0" and python_version >= "3.13") and extra == "optional-strict"
Requires-Dist: Levenshtein==0.23.0; (python_version < "3.13" and python_version >= "3.12") and extra == "optional-strict"
Requires-Dist: Levenshtein==0.20.3; (python_version < "3.12" and python_version >= "3.11") and extra == "optional-strict"
Requires-Dist: Levenshtein==0.18.2; (python_version < "3.11" and python_version >= "3.10") and extra == "optional-strict"
Requires-Dist: Levenshtein==0.18.0; (python_version < "3.10" and python_version >= "3.9") and extra == "optional-strict"
Requires-Dist: Levenshtein==0.18.0; (python_version < "3.9" and python_version >= "3.8") and extra == "optional-strict"
Requires-Dist: Levenshtein==0.18.0; (python_version < "3.8" and python_version >= "3.7") and extra == "optional-strict"
Requires-Dist: Levenshtein==0.18.0; (python_version < "3.7" and python_version >= "3.6") and extra == "optional-strict"
Requires-Dist: fire==0.5.0; python_version >= "3.10" and extra == "optional-strict"
Requires-Dist: fire==0.4.0; python_version < "3.10" and extra == "optional-strict"
Requires-Dist: line_profiler==4.2.0; (python_version < "4.0" and python_version >= "3.13") and extra == "optional-strict"
Requires-Dist: line_profiler==4.1.2; (python_version < "3.13" and python_version >= "3.12") and extra == "optional-strict"
Requires-Dist: line_profiler==4.1.0; (python_version < "3.12" and python_version >= "3.11") and extra == "optional-strict"
Requires-Dist: line_profiler==4.1.0; (python_version < "3.11" and python_version >= "3.10") and extra == "optional-strict"
Requires-Dist: line_profiler==4.1.0; (python_version < "3.10" and python_version >= "3.9") and extra == "optional-strict"
Requires-Dist: line_profiler==4.1.0; (python_version < "3.9" and python_version >= "3.8") and extra == "optional-strict"
Requires-Dist: line_profiler==4.1.0; (python_version < "3.8" and python_version >= "3.7") and extra == "optional-strict"
Requires-Dist: line_profiler==4.1.0; (python_version < "3.7" and python_version >= "3.6") and extra == "optional-strict"
Requires-Dist: yapf==0.16.3; extra == "optional-strict"
Requires-Dist: autoflake==1.5.0; extra == "optional-strict"
Requires-Dist: parso==0.8.4; (python_version < "4.0" and python_version >= "3.12") and extra == "optional-strict"
Requires-Dist: parso==0.8.3; (python_version < "3.12" and python_version >= "3.11") and extra == "optional-strict"
Requires-Dist: parso==0.8.0; python_version < "3.11" and extra == "optional-strict"
Requires-Dist: pint==0.24.4; (python_version < "4.0" and python_version >= "3.13") and extra == "optional-strict"
Requires-Dist: pint==0.23; (python_version < "3.13" and python_version >= "3.12") and extra == "optional-strict"
Requires-Dist: pint==0.18; (python_version < "3.12" and python_version >= "3.11") and extra == "optional-strict"
Requires-Dist: pint==0.18; (python_version < "3.11" and python_version >= "3.10") and extra == "optional-strict"
Requires-Dist: pint==0.18; (python_version < "3.10" and python_version >= "3.9") and extra == "optional-strict"
Requires-Dist: pint==0.18; (python_version < "3.9" and python_version >= "3.8") and extra == "optional-strict"
Requires-Dist: python_dateutil==2.8.2; extra == "optional-strict"
Requires-Dist: pytimeparse==1.1.8; extra == "optional-strict"
Provides-Extra: docs-strict
Requires-Dist: sphinx==4.3.2; extra == "docs-strict"
Requires-Dist: sphinx-autobuild==2021.3.14; extra == "docs-strict"
Requires-Dist: sphinx_rtd_theme==1.0.0; extra == "docs-strict"
Requires-Dist: sphinxcontrib-napoleon==0.7; extra == "docs-strict"
Requires-Dist: sphinx-autoapi==1.8.4; extra == "docs-strict"
Requires-Dist: Pygments==2.9.0; extra == "docs-strict"
Requires-Dist: myst_parser==0.16.1; extra == "docs-strict"
Requires-Dist: sphinx-reredirects==0.0.1; extra == "docs-strict"
Dynamic: author
Dynamic: author-email
Dynamic: classifier
Dynamic: description
Dynamic: description-content-type
Dynamic: home-page
Dynamic: license
Dynamic: provides-extra
Dynamic: requires-dist
Dynamic: requires-python
Dynamic: summary
